pydantic_collections/__init__.py
pydantic_collections/__init__.pyi
pydantic_collections/_v1.py
pydantic_collections/_v2.py
pydantic_collections-0.6.0.dist-info/LICENSE.txt
pydantic_collections-0.6.0.dist-info/METADATA
pydantic_collections-0.6.0.dist-info/WHEEL
pydantic_collections-0.6.0.dist-info/top_level.txt
pydantic_collections-0.6.0.dist-info/RECORD
