Metadata-Version: 2.1
Name: pydantic-collections
Version: 0.6.0
Summary: Collections of pydantic models
Home-page: https://github.com/romis2012/pydantic-collections
Author: Roman Snegirev
Author-email: snegiryev@gmail.com
License: Apache 2
Keywords: python pydantic validation parsing serialization models
License-File: LICENSE.txt
Requires-Dist: pydantic <3.0,>=1.8.2
Requires-Dist: typing-extensions >=4.7.1
